pypkgs_huan/__init__.py
pypkgs_huan/pypkgs_huan.py
pypkgs_huan-0.1.0.dist-info/LICENSE
pypkgs_huan-0.1.0.dist-info/WHEEL
pypkgs_huan-0.1.0.dist-info/METADATA
pypkgs_huan-0.1.0.dist-info/RECORD
